openqaoa_qiskit/__init__.py
openqaoa_qiskit/_version.py
openqaoa_qiskit/backend_config.py
openqaoa_qiskit/backends/__init__.py
openqaoa_qiskit/backends/devices.py
openqaoa_qiskit/backends/gates_qiskit.py
openqaoa_qiskit/backends/qaoa_qiskit_qpu.py
openqaoa_qiskit/backends/qaoa_qiskit_sim.py
openqaoa_qiskit-0.2.6.dist-info/LICENSE
openqaoa_qiskit-0.2.6.dist-info/METADATA
openqaoa_qiskit-0.2.6.dist-info/WHEEL
openqaoa_qiskit-0.2.6.dist-info/entry_points.txt
openqaoa_qiskit-0.2.6.dist-info/top_level.txt
openqaoa_qiskit-0.2.6.dist-info/RECORD
